Metadata-Version: 1.1
Name: opendem
Version: 0.0.2
Summary: Very simple API to download, merge, resample, project DEM tiles from AWS and Thredds
Home-page: https://github.com/dgketchum
Author: David Ketchum
Author-email: dgketchum@gmail.com
License: Apache
Download-URL: https://github.com/dgketchum/dem/archive/0.0.2.tar.gz
Keywords: DEM digital elevation model
Platform: Posix; MacOS X; Windows
Classifier: Development Status :: 3 - Alpha
Classifier: Intended Audience :: Science/Research
Classifier: Topic :: Scientific/Engineering :: GIS
Classifier: License :: OSI Approved :: Apache Software License
Classifier: Programming Language :: Python :: 2.7
Classifier: Programming Language :: Python :: 3.6
